aa_skip_email/__init__.py
aa_skip_email/app_settings.py
aa_skip_email/authentication/backends.py
aa_skip_email/helpers.py
aa_skip_email/management/__init__.py
aa_skip_email/management/commands/__init__.py
aa_skip_email/management/commands/fill_missing_emails.py
aa_skip_email/tasks.py
aa_skip_email-0.2.2.dist-info/WHEEL
aa_skip_email-0.2.2.dist-info/METADATA
aa_skip_email-0.2.2.dist-info/RECORD
