Metadata-Version: 2.4
Name: aa-skip-email
Version: 0.2.2
Summary: Allows you to skip entering your email after registering via EVE SSO
Author: Boris Talovikov
Author-email: Boris Talovikov <boris@talovikov.ru>
License-Expression: GPL-3.0-or-later
Classifier: Programming Language :: Python :: 3
Classifier: Programming Language :: Python :: 3.10
Classifier: Programming Language :: Python :: 3.11
Classifier: Programming Language :: Python :: 3.12
Classifier: Programming Language :: Python :: 3.13
Classifier: Programming Language :: Python :: 3.14
Requires-Dist: allianceauth>=3.6
Maintainer: Boris Blade Artrald
Maintainer-email: Boris Blade Artrald <boris-blade-artrald@eveo7.ru>
Requires-Python: >=3.10
Project-URL: Repository, https://gitlab.com/zima-corp/aa-skip-email
